<annotation>
	<folder>cassiopeia</folder>
	<filename>cassiopeia_00068.jpg</filename>
	<path>C:\Users\easmsma\Desktop\projects\constellano\inception\training\dataset\cassiopeia\cassiopeia_00068.jpg</path>
	<source>
		<database>Unknown</database>
	</source>
	<size>
		<width>500</width>
		<height>500</height>
		<depth>1</depth>
	</size>
	<segmented>0</segmented>
	<object>
		<name>cassiopeia</name>
		<pose>Unspecified</pose>
		<truncated>0</truncated>
		<difficult>0</difficult>
		<bndbox>
			<xmin>144</xmin>
			<ymin>57</ymin>
			<xmax>212</xmax>
			<ymax>194</ymax>
		</bndbox>
	</object>
</annotation>
